Workbook

Sheet Start_Here
A1: PRICING INTELLIGENCE — INITIAL DATA WORKBOOK
A3: Purpose | B3: Capture company context, economics, operating constraints and historical price-demand data for the pricing engine.
A4: Default period | B4: Monthly is the default for most businesses. Use the same period for cost planning, target volume and fixed costs.
A5: Next step | B5: Step 2 will validate the historical data and run EDA before demand forecasting, elasticity and causal estimation.
A6: Important | B6: Do not guess elasticity or willingness-to-pay here. Estimate them later or use documented external priors.
A7: Packaging | B7: Packaging that scales with units is normally variable cost. Keep it separate so its economics are visible.
A8: Labour | B8: Permanent salaries are generally fixed. Piece-rate/output labour is variable. Overtime/extra shifts can be step or semi-variable.
A9: Historical minimum | B9: Date + product + price + quantity. Revenue, competitor price, promotion, inventory, location and channel materially improve the model.
A10: Tabs | B10: Company_Context | Cost_Structure | Constraints | Historical_Data | Definitions | Dashboard

Sheet Company_Context
A1: 01 — COMPANY & PRODUCT CONTEXT
A3: Company & Product | E3: Market Position & Price Leader
A4: Field | B4: Input | C4: Guidance | E4: Field | F4: Input | G4: Derived / Guidance | H4: Status
A5: Company name | B5: bishanlal babulal | C5: Legal or operating brand name | E5: Price leader? | F5: no(rank 6) | G5: If No, enter leader below | H5: =IF(F5="Yes","Leader selected","Follower setup") -> Follower setup
A6: Business category | B6: food | C6: e.g. Packaged Food, Chemicals, SaaS | E6: Price leader / competitor | F6: bikaji | G6: Named reference competitor | H6: =IF(F5="No",IF(F6<>"","OK","Enter leader name"),"N/A") -> N/A
A7: Product name | B7: 1kg bikaneri bhujia | C7: Primary product being priced | E7: Leader current base price | F7: 260 | G7: Before tax/discount
A8: Product type | B8: fmcg | C8: FMCG, B2B service, software, industrial product, etc. | E8: Our current base price | F8: 280 | G8: Before tax/discount
A9: Market / country | B9: India | C9: Primary market | E9: Price gap | F9: =F8-F7 -> 20 | G9: Our price − leader price | H9: =IF(F5="Yes","N/A",IF(F7>0,"Calculated","—")) -> Calculated
A10: Primary channel | B10: Both | C10: Online / Offline / Both | E10: Relative price | F10: =IF(F8>0,F8/F7,0) -> 1.0769231 | G10: Our price ÷ leader price
A11: primary region | B11: rajasthan particulary bikaner | E11: Positioning note | F11: premium | G11: Premium / parity / value / unknown
A12: overall region | B12: india
A14: Current Price & Tax
A15: Field | B15: Input | C15: Guidance
A16: Current base price(before tax) | B16: 267 | C16: Price before GST/tax
A17: GST / tax rate | B17: 5 | C17: Applicable rate
A18: Current discount | B18: 0 | C18: Optional current discount
A19: Tax amount / unit | B19: =B16*B17/100 -> 13.35 | C19: Calculated
A20: Price after tax | B20: =B16+B19 -> 280.35 | C20: Calculated before discount
A21: Current discount | B21: 0 | C21: assumption
A22: Effective customer price | B22: =B20*(1-B18/100) -> 280.35 | C22: After tax and current discount
A23: retailer commission | B23: 0.1 | C23: assuming : taking an avg as talk with other retailers

Sheet Cost_Structure
A1: 02 — COST STRUCTURE
A3: Cost Planning Period
A4: Field | B4: Input | C4: Unit | D4: Guidance
A5: Cost period | B5: Monthly | C5: — | D5: Same period used for fixed cost + target volume
A6: current volume production | B6: 15000 | C6: units / period | D6: saleable volume for planning/allocation
A7: Fixed cost / selected period | B7: =C30 -> 448000 | C7: ₹ / period | D7: Calculated from fixed-cost section below
A8: current profit / unit | B8: =B41 -> 56.433333 | C8: ₹ / unit | D8: Optional cost-plus reference, not the final optimized price
A9: unit sold | B9: 13000 | C9: unit/period
A10: Variable Costs — normally scale with units
A11: Cost type | B11: Cost item | C11: ₹ / unit | D11: Included? | E11: Examples / guidance
A12: Variable | B12: Raw material / ingredients | C12: =E61 -> 104 | D12: Yes | E12: Inputs consumed per unit(mainly in oil)
A13: Variable | B13: Packaging | C13: 20 | D13: Yes | E13: Pouch, carton, label, seal, bottle, cap, tray
A14: Variable | B14: karigar | C14: 7 | D14: Yes | E14: output-linked labour
A15: Variable | B15: Logistics / fulfilment | C15: 20 | D15: Yes | E15: Per-unit freight, delivery or fulfilment
A16: Variable | B16: Sales / payment fees | C16: =Company_Context!B16*0.1 -> 26.7 | D16: Yes | E16: Commission, marketplace fee, payment fee of the sales man, distributors
A17: Variable | B17: cost of electricty | C17: 3 | D17: Optional | E17: Any other per-unit cost
B18: Total variable cost / unit | C18: =SUM(C12:C17) -> 180.7
B19: Contribution at current base price | C19: =Company_Context!B16-C18 -> 86.3 | E19: Current base price − variable cost
A21: Fixed Costs — generally stable within the selected period
A22: Cost type | B22: Cost item | C22: ₹ / selected period | D22: Included? | E22: Examples / guidance
A23: Fixed | B23: Rent / facility | C23: 40000 | D23: Yes | E23: Factory, warehouse, office rent
A24: Fixed | B24: Permanent salaries | C24: =D54 -> 310000 | D24: Yes | E24: Management/admin/production salaries that do not scale directly with units
A25: Fixed | B25: electricity | C25: 70000 | D25: yes | E25: cost of the electricity(excluding the frying )
A26: Fixed | B26: Administrative expenses | C26: 3000 | D26: yes | E26: Office/admin overhead
A27: fixed | B27: returns/ damaged | C27: 5000 | D27: yes | E27: usually not very much around 10 boxes per month 10 damaged total 20
A28: fixed | B28: marketing promotion | C28: 10000 | D28: Optional | E28: instagram , banners ads
A29: Fixed | B29: Other fixed costs | C29: 10000 | D29: Optional | E29: Other stable operating costs
A30: fixed | B30: Total fixed cost / period | C30: =SUM(C23:C29) -> 448000
B31: Fixed cost / target unit | C31: =IF(B6>0,C30/B6,0) -> 29.866667 | E31: Total fixed cost ÷ volume
A34: Cost Reference Outputs
A35: Metric | B35: Formula output | C35: Why it matters | D35: Reference
A36: Variable cost / unit | B36: =C18 -> 180.7 | C36: Economic contribution floor | D36: Used in profit optimization
A37: Fixed cost / period | B37: =C30 -> 448000 | C37: Period-level operating obligation | D37: Keep separate from variable cost
A38: Fixed cost / target unit | B38: =C31 -> 29.866667 | C38: Useful for full-cost / break-even analysis | D38: Reference only
A39: Indicative full cost / unit | B39: =B36+B38 -> 210.56667 | C39: Variable + allocated fixed cost | D39: Cost-plus benchmark, not final optimized price
A40: Current contribution / unit | B40: =Company_Context!B16-B36 -> 86.3 | C40: Base price − variable cost | D40: Margin analysis
A41: profit per box | B41: =Company_Context!B16-B39 -> 56.433333
A47: salaries breakdown
A48: role | B48: no. | C48: salaries | D48: final cost
A49: C.A | B49: 1 | C49: 50000 | D49: =B49*C49 -> 50000
A50: accountent | B50: 1 | C50: 30000 | D50: =B50*C50 -> 30000
A51: karigar | B51: 5 | C51: 15000 | D51: =B51*C51 -> 75000
A52: sales man | B52: 4 | C52: 20000 | D52: =B52*C52 -> 80000
A53: workers | B53: 5 | C53: 15000 | D53: =B53*C53 -> 75000
C54: total cost | D54: =SUM(D49:D53) -> 310000
A55: raw material cost
A56: material | B56: share | C56: Quantity Needed | D56: Bulk Rate Assumed/kg | E56: calcuated cost/unit
A57: Moth Dal Flour | B57: 0.505 | C57: 505g | D57: 90 | E57: =D57*B57 -> 45.45
A58: Gram Flour (Besan) | B58: 0.115 | C58: 115g | D58: 70 | E58: =D58*B58 -> 8.05
A59: Refined Cottonseed Oil(aborsorbed) | B59: 0.35 | C59: 350g | D59: 110 | E59: =D59*B59 -> 38.5
A60: Spices & Condiments(low quantity) | B60: 0.03 | C60: ~30 g | D60: 400 | E60: =D60*B60 -> 12
A61: Total Raw Material Cost | B61: 1 | C61: 1,000 g | E61: =SUM(E57:E60) -> 104
A63: range of the raw materials
A64: material | B64: price
A65: Moth Dal Flour | B65: 70-110
A66: Gram Flour (Besan) | B66: 60-80
A67: Refined Cottonseed Oil(aborsorbed) | B67: 100-120
A68: Spices & Condiments(low quantity) | B68: 350-450

Sheet competitive_analysis
B2: Competitive data: 1 kg packs, shelf price (MRP = selling price)
B3: Blue = input. Perception, quality and taste scores are ASSUMPTIONS from the owner's experience (no survey, no sample); treat results as a diagnostic, not evidence.
B5: Brand | C5: Role | D5: Pack (kg) | E5: Shelf price (₹) | F5: Perception (0-10) | G5: Quality (0-10) | H5: Taste (0-10) | I5: Composite benefit | J5: Price per kg (₹) | K5: Gap vs ours (₹) | L5: Relative to leader | M5: Price per benefit point (₹)
B6: Bikaji | C6: Leader | D6: 1 | E6: 260 | F6: 9 | G6: 7 | H6: 8.5 | I6: 8.1666667 | J6: 260 | K6: -20 | L6: 1 | M6: 31.836735
B7: Haldiram | C7: Competitor | D7: 1 | E7: 270 | F7: 8.5 | G7: 7 | H7: 8 | I7: 7.8333333 | J7: 270 | K7: -10 | L7: 1.0384615 | M7: 34.468085
B8: Bikano | C8: Competitor | D8: 1 | E8: 280 | F8: 8 | G8: 8 | H8: 8.5 | I8: 8.1666667 | J8: 280 | K8: 0 | L8: 1.0769231 | M8: 34.285714
B9: Bhikaram Chandmal | C9: Competitor (local) | D9: 1 | E9: 250 | F9: 8.5 | G9: 8 | H9: 8.8 | I9: 8.4333333 | J9: 250 | K9: -30 | L9: 0.96153846 | M9: 29.644269
B10: Bishanlal Babulal | C10: Our brand | D10: 1 | E10: 280 | F10: 9 | G10: 8 | H10: 9 | I10: 8.6666667 | J10: 280 | K10: 0 | L10: 1.0769231 | M10: 32.307692
B11: Composite = simple average of perception, quality and taste (equal weights are an assumption).
B13: Fit-line helper (competitors only) | C13: Benefit (x) | D13: Fair price (y)
B14: Left end | C14: 7.7333333 | D14: 278.03681
B15: Right end | C15: 8.7666667 | D15: 245.70552
B37: Candidate prices vs the market
B38: Shelf price (₹) | C38: Gap vs leader (₹) | D38: Relative to leader | E38: Relative to competitor avg | F38: Cheaper competitors (of 4) | G38: Within leader cap | H38: Feasibility result
B39: 259 | C39: -1 | D39: 0.99615385 | E39: 0.97735849 | F39: 1 | G39: Yes | H39: Breaks step limit
B40: 266.33 | C40: 6.33 | D40: 1.0243462 | E40: 1.0050189 | F40: 2 | G40: Yes | H40: Feasible
B41: 269 | C41: 9 | D41: 1.0346154 | E41: 1.0150943 | F41: 2 | G41: Yes | H41: Feasible
B42: 272 | C42: 12 | D42: 1.0461538 | E42: 1.0264151 | F42: 3 | G42: Yes | H42: Feasible
B43: 275 | C43: 15 | D43: 1.0576923 | E43: 1.0377358 | F43: 3 | G43: Yes | H43: Feasible
B44: 279 | C44: 19 | D44: 1.0730769 | E44: 1.0528302 | F44: 3 | G44: Yes | H44: Feasible
B45: 280 | C45: 20 | D45: 1.0769231 | E45: 1.0566038 | F45: 3 | G45: Yes | H45: Feasible
B46: 289 | C46: 29 | D46: 1.1115385 | E46: 1.090566 | F46: 4 | G46: No | H46: Needs new MRP

Sheet constraints
A1: Constraint | B1: Value | C1: Unit | D1: Basis
A2: Other variable cost (excl. retailer margin) | B2: 154 | C2: ₹ / unit | D2: Total variable cost minus retailer margin
A3: Retailer margin | B3: 0.1 | C3: % of price | D3: Scales with price, not a flat ₹27
A4: Zero-contribution price (safety stop) | B4: 171.11111 | C4: ₹ pre-tax | D4: Other variable cost ÷ (1 − margin)
A5: Full-cost break-even price (reference) | B5: 209.40171 | C5: ₹ pre-tax | D5: Covers variable and fixed cost at current volume
A6: MRP, shelf | B6: 280 | C6: ₹ shelf | D6: Legal cap
A7: MRP, pre-tax equivalent (price ceiling) | B7: 266.66667 | C7: ₹ pre-tax | D7: MRP ÷ (1 + GST)
A8: Step-limit low | B8: 253.65 | C8: ₹ pre-tax | D8: Current price less max decrease
A9: Step-limit high | B9: 275 | C9: ₹ pre-tax | D9: Current price plus max increase
A10: min-limit MRP | B10: 265 | C10: post tax | D10: current price plus gst
A11: max-limit MRP | B11: 288 | C11: post tax | D11: max price + gst
A12: max volume | B12: 17000
A13: min volume | B13: 13000
A14: minimum profit | B14: 650000
A15: max profit based on max volume | B15: 850000
A16: shelf life | B16: 6 months
A17: price -bandwidth | B17: 265-288
A18: Price review cadence | B18: Monthly | D18: Governance
A19: Legal / tax | B19: GST 5%; price must not exceed printed MRP | D19: Verify rate against current CBIC schedule

Sheet data_historical
A1: week_start | B1: shelf_price | C1: leader_price | D1: other_comp_avg_price | E1: festival | F1: oil_price_per_kg | G1: other_variable_cost | H1: price_change | I1: units_sold | J1: distribution | K1: distribution | L1: promotion | M1: log price | N1: log_leader_price | O1: other_comp | P1: log_units_sold | Q1: festival_peak | R1: festival_buildup | S1: units_sold_old | T1: log_distribution | U1: log_promotion
A2: 45201 | B2: 220 | C2: 200 | D2: 216.67 | F2: 100.72 | G2: 141.01 | I2: 2375 | J2: =K2/2 -> 49.5 | K2: 99 | L2: 5 | M2: 5.3936275 | N2: 5.2983174 | O2: 5.3783755 | P2: 7.7727527 | Q2: 0 | R2: 0 | S2: 2141 | T2: 4.5938059 | U2: 2.1860513
A3: 45208 | B3: 220 | C3: 200 | D3: 216.67 | E3: Diwali (build-up) | F3: 100.78 | G3: 141.09 | I3: 3110 | J3: =K3/2 -> 49 | K3: 98 | L3: 5 | M3: 5.3936275 | N3: 5.2983174 | O3: 5.3783755 | P3: 8.042378 | Q3: 0 | R3: 1 | S3: 2536 | T3: 4.5894472 | U3: 2.4484155
A4: 45215 | B4: 220 | C4: 200 | D4: 216.67 | E4: Diwali (build-up) | F4: 100.84 | G4: 141.17 | I4: 3133 | J4: =K4/2 -> 48.5 | K4: 97 | L4: 6 | M4: 5.3936275 | N4: 5.2983174 | O4: 5.3783755 | P4: 8.0497463 | Q4: 0 | R4: 1 | S4: 3487 | T4: 4.5797498 | U4: 2.4150205
A5: 45222 | B5: 220 | C5: 200 | D5: 216.67 | E5: Diwali (build-up) | F5: 100.89 | G5: 141.25 | I5: 3285 | J5: =K5/2 -> 49.5 | K5: 99 | L5: 5 | M5: 5.3936275 | N5: 5.2983174 | O5: 5.3783755 | P5: 8.0971219 | Q5: 0 | R5: 1 | S5: 4580 | T5: 4.5911727 | U5: 2.3253246
A6: 45229 | B6: 220 | C6: 200 | D6: 216.67 | E6: Diwali (build-up) | F6: 100.95 | G6: 141.33 | I6: 3403 | J6: =K6/2 -> 50 | K6: 100 | L6: 4 | M6: 5.3936275 | N6: 5.2983174 | O6: 5.3783755 | P6: 8.1324127 | Q6: 0 | R6: 1 | S6: 4856 | T6: 4.6085644 | U6: 2.5265283
A7: 45236 | B7: 220 | C7: 200 | D7: 216.67 | E7: Diwali (peak week) | F7: 101.01 | G7: 141.41 | I7: 4589 | J7: =K7/2 -> 50.5 | K7: 101 | L7: 6 | M7: 5.3936275 | N7: 5.2983174 | O7: 5.3783755 | P7: 8.4314174 | Q7: 1 | R7: 0 | S7: 4395 | T7: 4.6173952 | U7: 2.6056483
A8: 45243 | B8: 220 | C8: 200 | D8: 216.67 | F8: 101.07 | G8: 141.49 | I8: 2473 | J8: =K8/2 -> 51 | K8: 102 | L8: 4 | M8: 5.3936275 | N8: 5.2983174 | O8: 5.3783755 | P8: 7.8131873 | Q8: 0 | R8: 0 | S8: 1892 | T8: 4.6200588 | U8: 2.313525
A9: 45250 | B9: 220 | C9: 200 | D9: 216.67 | F9: 101.12 | G9: 141.57 | I9: 2427 | J9: =K9/2 -> 51 | K9: 102 | L9: 5 | M9: 5.3936275 | N9: 5.2983174 | O9: 5.3783755 | P9: 7.7944112 | Q9: 0 | R9: 0 | S9: 2116 | T9: 4.6207482 | U9: 2.2491843
A10: 45257 | B10: 220 | C10: 200 | D10: 216.67 | F10: 101.18 | G10: 141.65 | I10: 2370 | J10: =K10/2 -> 50.5 | K10: 101 | L10: 6 | M10: 5.3936275 | N10: 5.2983174 | O10: 5.3783755 | P10: 7.7706452 | Q10: 0 | R10: 0 | S10: 2283 | T10: 4.6145263 | U10: 2.346602
A11: 45264 | B11: 220 | C11: 200 | D11: 216.67 | F11: 101.24 | G11: 141.74 | I11: 2381 | J11: =K11/2 -> 50 | K11: 100 | L11: 6 | M11: 5.3936275 | N11: 5.2983174 | O11: 5.3783755 | P11: 7.7752758 | Q11: 0 | R11: 0 | S11: 2162 | T11: 4.6056701 | U11: 2.2679936
A12: 45271 | B12: 220 | C12: 200 | D12: 216.67 | F12: 101.3 | G12: 141.82 | I12: 2641 | J12: =K12/2 -> 50 | K12: 100 | L12: 7 | M12: 5.3936275 | N12: 5.2983174 | O12: 5.3783755 | P12: 7.8789129 | Q12: 0 | R12: 0 | S12: 2433 | T12: 4.6095605 | U12: 2.3005831
A13: 45278 | B13: 220 | C13: 200 | D13: 216.67 | F13: 101.35 | G13: 141.9 | I13: 2344 | J13: =K13/2 -> 49 | K13: 98 | L13: 6 | M13: 5.3936275 | N13: 5.2983174 | O13: 5.3783755 | P13: 7.7596142 | Q13: 0 | R13: 0 | S13: 2505 | T13: 4.5814921 | U13: 2.2246236
A14: 45285 | B14: 220 | C14: 200 | D14: 216.67 | F14: 101.41 | G14: 141.98 | I14: 2218 | J14: =K14/2 -> 48 | K14: 96 | L14: 7 | M14: 5.3936275 | N14: 5.2983174 | O14: 5.3783755 | P14: 7.7043612 | Q14: 0 | R14: 0 | S14: 2399 | T14: 4.5627845 | U14: 2.2170272
A15: 45292 | B15: 220 | C15: 200 | D15: 216.67 | F15: 101.47 | G15: 142.06 | I15: 2171 | J15: =K15/2 -> 47 | K15: 94 | L15: 5 | M15: 5.3936275 | N15: 5.2983174 | O15: 5.3783755 | P15: 7.6829432 | Q15: 0 | R15: 0 | S15: 2572 | T15: 4.5403116 | U15: 2.4212566
A16: 45299 | B16: 220 | C16: 210 | D16: 216.67 | F16: 101.53 | G16: 142.14 | I16: 2229 | J16: =K16/2 -> 47.5 | K16: 95 | L16: 6 | M16: 5.3936275 | N16: 5.3471075 | O16: 5.3783755 | P16: 7.7093083 | Q16: 0 | R16: 0 | S16: 2577 | T16: 4.5508196 | U16: 2.2752139
A17: 45306 | B17: 220 | C17: 210 | D17: 216.67 | F17: 101.59 | G17: 142.22 | I17: 2116 | J17: =K17/2 -> 46.5 | K17: 93 | L17: 7 | M17: 5.3936275 | N17: 5.3471075 | O17: 5.3783755 | P17: 7.6572828 | Q17: 0 | R17: 0 | S17: 2314 | T17: 4.5371055 | U17: 2.3398809
A18: 45313 | B18: 220 | C18: 210 | D18: 216.67 | F18: 101.64 | G18: 142.3 | I18: 2050 | J18: =K18/2 -> 46.5 | K18: 93 | L18: 8 | M18: 5.3936275 | N18: 5.3471075 | O18: 5.3783755 | P18: 7.6255951 | Q18: 0 | R18: 0 | S18: 2466 | T18: 4.5336742 | U18: 2.3145137
A19: 45320 | B19: 220 | C19: 210 | D19: 216.67 | F19: 101.7 | G19: 142.38 | I19: 2300 | J19: =K19/2 -> 47.5 | K19: 95 | L19: 7 | M19: 5.3936275 | N19: 5.3471075 | O19: 5.3783755 | P19: 7.7406644 | Q19: 0 | R19: 0 | S19: 2275 | T19: 4.5542979 | U19: 2.2834023
... A25: 45362 | B25: 220 | C25: 210 | D25: 226.67 | F25: 102.05 | G25: 142.87 | I25: 2788 | J25: =K25/2 -> 49.5 | K25: 99 | L25: 8 | M25: 5.3936275 | N25: 5.3471075 | O25: 5.4234952 | P25: 7.9330798 | Q25: 0 | R25: 0 | S25: 2342 | T25: 4.5938059 | U25: 2.4185888
A26: 45369 | B26: 220 | C26: 210 | D26: 226.67 | E26: Holi (build-up) | F26: 102.11 | G26: 142.95 | I26: 3447 | J26: =K26/2 -> 49 | K26: 98 | L26: 7 | M26: 5.3936275 | N26: 5.3471075 | O26: 5.4234952 | P26: 8.1452596 | Q26: 0 | R26: 1 | S26: 2593 | T26: 4.5862931 | U26: 2.5408143
A27: 45376 | B27: 220 | C27: 210 | D27: 226.67 | E27: Holi (peak week) | F27: 102.16 | G27: 143.03 | I27: 4504 | J27: =K27/2 -> 48.5 | K27: 97 | L27: 9 | M27: 5.3936275 | N27: 5.3471075 | O27: 5.4234952 | P27: 8.4127212 | Q27: 1 | R27: 0 | S27: 3033 | T27: 4.5739891 | U27: 2.6567569
A28: 45383 | B28: 220 | C28: 210 | D28: 226.67 | F28: 102.22 | G28: 143.11 | I28: 2174 | J28: =K28/2 -> 48 | K28: 96 | L28: 9.8 | M28: 5.3936275 | N28: 5.3471075 | O28: 5.4234952 | P28: 7.6843241 | Q28: 0 | R28: 0 | S28: 2285 | T28: 4.5679874 | U28: 2.2823824
A29: 45390 | B29: 230 | C29: 210 | D29: 226.67 | F29: 102.28 | G29: 143.19 | H29: Regular increase | I29: 2207 | J29: =K29/2 -> 50.5 | K29: 101 | L29: 11 | M29: 5.4380793 | N29: 5.3471075 | O29: 5.4234952 | P29: 7.6993894 | Q29: 0 | R29: 0 | S29: 2293 | T29: 4.6145263 | U29: 2.2170272
A30: 45397 | B30: 230 | C30: 210 | D30: 226.67 | F30: 102.34 | G30: 143.27 | I30: 2519 | J30: =K30/2 -> 50.5 | K30: 101 | L30: 8 | M30: 5.4380793 | N30: 5.3471075 | O30: 5.4234952 | P30: 7.8316173 | Q30: 0 | R30: 0 | S30: 2312 | T30: 4.6130391 | U30: 2.4051417
A31: 45404 | B31: 230 | C31: 210 | D31: 226.67 | F31: 102.4 | G31: 143.36 | I31: 2570 | J31: =K31/2 -> 50.5 | K31: 101 | L31: 9 | M31: 5.4380793 | N31: 5.3471075 | O31: 5.4234952 | P31: 7.8516612 | Q31: 0 | R31: 0 | S31: 2326 | T31: 4.6150215 | U31: 2.4069451
A32: 45411 | B32: 230 | C32: 210 | D32: 226.67 | F32: 102.46 | G32: 143.44 | I32: 2366 | J32: =K32/2 -> 51 | K32: 102 | L32: 10 | M32: 5.4380793 | N32: 5.3471075 | O32: 5.4234952 | P32: 7.768956 | Q32: 0 | R32: 0 | S32: 2660 | T32: 4.6265402 | U32: 2.3194422
A33: 45418 | B33: 230 | C33: 210 | D33: 226.67 | F33: 102.51 | G33: 143.52 | I33: 2375 | J33: =K33/2 -> 52 | K33: 104 | L33: 12 | M33: 5.4380793 | N33: 5.3471075 | O33: 5.4234952 | P33: 7.7727527 | Q33: 0 | R33: 0 | S33: 2102 | T33: 4.6401512 | U33: 2.3749058
A34: 45425 | B34: 230 | C34: 210 | D34: 226.67 | F34: 102.57 | G34: 143.6 | I34: 2409 | J34: =K34/2 -> 52 | K34: 104 | L34: 12 | M34: 5.4380793 | N34: 5.3471075 | O34: 5.4234952 | P34: 7.786967 | Q34: 0 | R34: 0 | S34: 1995 | T34: 4.6466 | U34: 2.3951643
A35: 45432 | B35: 230 | C35: 210 | D35: 226.67 | F35: 102.63 | G35: 143.68 | I35: 2553 | J35: =K35/2 -> 53 | K35: 106 | L35: 11 | M35: 5.4380793 | N35: 5.3471075 | O35: 5.4234952 | P35: 7.8450244 | Q35: 0 | R35: 0 | S35: 1924 | T35: 4.662023 | U35: 2.3997118
A36: 45439 | B36: 230 | C36: 210 | D36: 226.67 | F36: 102.69 | G36: 143.76 | I36: 2597 | J36: =K36/2 -> 53.5 | K36: 107 | L36: 10 | M36: 5.4380793 | N36: 5.3471075 | O36: 5.4234952 | P36: 7.8621122 | Q36: 0 | R36: 0 | S36: 2126 | T36: 4.6747895 | U36: 2.4078456
A37: 45446 | B37: 230 | C37: 210 | D37: 226.67 | F37: 102.75 | G37: 143.85 | I37: 2453 | J37: =K37/2 -> 52 | K37: 104 | L37: 9.96 | M37: 5.4380793 | N37: 5.3471075 | O37: 5.4234952 | P37: 7.805067 | Q37: 0 | R37: 0 | S37: 2283 | T37: 4.6480381 | U37: 2.2985771
A38: 45453 | B38: 230 | C38: 210 | D38: 226.67 | F38: 102.81 | G38: 143.93 | I38: 2653 | J38: =K38/2 -> 53 | K38: 106 | L38: 9 | M38: 5.4380793 | N38: 5.3471075 | O38: 5.4234952 | P38: 7.8834464 | Q38: 0 | R38: 0 | S38: 2125 | T38: 4.6608887 | U38: 2.457878
A39: 45460 | B39: 230 | C39: 210 | D39: 226.67 | F39: 102.86 | G39: 144.01 | I39: 2506 | J39: =K39/2 -> 54 | K39: 108 | L39: 10 | M39: 5.4380793 | N39: 5.3471075 | O39: 5.4234952 | P39: 7.8264431 | Q39: 0 | R39: 0 | S39: 1972 | T39: 4.6801849 | U39: 2.2375131
A40: 45467 | B40: 230 | C40: 210 | D40: 226.67 | F40: 102.92 | G40: 144.09 | I40: 2529 | J40: =K40/2 -> 52.5 | K40: 105 | L40: 11 | M40: 5.4380793 | N40: 5.3471075 | O40: 5.4234952 | P40: 7.8355792 | Q40: 0 | R40: 0 | S40: 1934 | T40: 4.6515766 | U40: 2.4069451
A41: 45474 | B41: 230 | C41: 210 | D41: 226.67 | F41: 102.98 | G41: 144.17 | I41: 2612 | J41: =K41/2 -> 53.5 | K41: 107 | L41: 12 | M41: 5.4380793 | N41: 5.3471075 | O41: 5.4234952 | P41: 7.8678715 | Q41: 0 | R41: 0 | S41: 2343 | T41: 4.671426 | U41: 2.3786198
... A46: 45509 | B46: 230 | C46: 220 | D46: 226.67 | F46: 103.27 | G46: 144.58 | I46: 2754 | J46: =K46/2 -> 55.5 | K46: 111 | L46: 13 | M46: 5.4380793 | N46: 5.3936275 | O46: 5.4234952 | P46: 7.9208097 | Q46: 0 | R46: 0 | S46: 2409 | T46: 4.7071851 | U46: 2.2082744
A47: 45516 | B47: 230 | C47: 220 | D47: 226.67 | E47: Raksha Bandhan (build-up) | F47: 103.33 | G47: 144.67 | I47: 3520 | J47: =K47/2 -> 54.5 | K47: 109 | L47: 14 | M47: 5.4380793 | N47: 5.3936275 | O47: 5.4234952 | P47: 8.1662163 | Q47: 0 | R47: 1 | S47: 2680 | T47: 4.6929979 | U47: 2.5710843
A48: 45523 | B48: 230 | C48: 220 | D48: 226.67 | E48: Raksha Bandhan (peak week) | F48: 103.39 | G48: 144.75 | I48: 5170 | J48: =K48/2 -> 56 | K48: 112 | L48: 15 | M48: 5.4380793 | N48: 5.3936275 | O48: 5.4234952 | P48: 8.550628 | Q48: 1 | R48: 0 | S48: 3219 | T48: 4.7213519 | U48: 2.5649494
A49: 45530 | B49: 230 | C49: 220 | D49: 226.67 | F49: 103.45 | G49: 144.83 | I49: 2537 | J49: =K49/2 -> 55.5 | K49: 111 | L49: 12 | M49: 5.4380793 | N49: 5.3936275 | O49: 5.4234952 | P49: 7.8387376 | Q49: 0 | R49: 0 | S49: 2496 | T49: 4.7100706 | U49: 2.3456446
A50: 45537 | B50: 230 | C50: 220 | D50: 226.67 | F50: 103.51 | G50: 144.91 | I50: 2582 | J50: =K50/2 -> 56 | K50: 112 | L50: 13 | M50: 5.4380793 | N50: 5.3936275 | O50: 5.4234952 | P50: 7.8563196 | Q50: 0 | R50: 0 | S50: 2566 | T50: 4.7189452 | U50: 2.4150205
A51: 45544 | B51: 230 | C51: 220 | D51: 226.67 | F51: 103.57 | G51: 144.99 | I51: 2699 | J51: =K51/2 -> 56.5 | K51: 113 | L51: 14 | M51: 5.4380793 | N51: 5.3936275 | O51: 5.4234952 | P51: 7.9006366 | Q51: 0 | R51: 0 | S51: 2474 | T51: 4.7280071 | U51: 2.2170272
A52: 45551 | B52: 230 | C52: 220 | D52: 226.67 | F52: 103.63 | G52: 145.08 | I52: 2713 | J52: =K52/2 -> 55.5 | K52: 111 | L52: 13 | M52: 5.4380793 | N52: 5.3936275 | O52: 5.4234952 | P52: 7.9058103 | Q52: 0 | R52: 0 | S52: 2493 | T52: 4.7132171 | U52: 2.1804175
A53: 45558 | B53: 230 | C53: 220 | D53: 226.67 | F53: 103.69 | G53: 145.16 | I53: 2866 | J53: =K53/2 -> 56.5 | K53: 113 | L53: 15 | M53: 5.4380793 | N53: 5.3936275 | O53: 5.4234952 | P53: 7.9606726 | Q53: 0 | R53: 0 | S53: 2570 | T53: 4.7234864 | U53: 2.3711779
A54: 45565 | B54: 230 | C54: 220 | D54: 226.67 | E54: Diwali (build-up) | F54: 103.74 | G54: 145.24 | I54: 3605 | J54: =K54/2 -> 57 | K54: 114 | L54: 12 | M54: 5.4380793 | N54: 5.3936275 | O54: 5.4234952 | P54: 8.190077 | Q54: 0 | R54: 1 | S54: 2881 | T54: 4.7318028 | U54: 2.5160823
A55: 45572 | B55: 230 | C55: 220 | D55: 226.67 | E55: Diwali (build-up) | F55: 103.8 | G55: 145.32 | I55: 3672 | J55: =K55/2 -> 57 | K55: 114 | L55: 13 | M55: 5.4380793 | N55: 5.3936275 | O55: 5.4234952 | P55: 8.2084918 | Q55: 0 | R55: 1 | S55: 3706 | T55: 4.7353209 | U55: 2.4940316
A56: 45579 | B56: 230 | C56: 220 | D56: 226.67 | E56: Diwali (build-up) | F56: 103.86 | G56: 145.41 | I56: 3624 | J56: =K56/2 -> 56.5 | K56: 113 | L56: 14 | M56: 5.4380793 | N56: 5.3936275 | O56: 5.4234952 | P56: 8.1953337 | Q56: 0 | R56: 1 | S56: 4650 | T56: 4.7241081 | U56: 2.5176965
A57: 45586 | B57: 230 | C57: 220 | D57: 226.67 | E57: Diwali (build-up) | F57: 103.92 | G57: 145.49 | I57: 3782 | J57: =K57/2 -> 56.5 | K57: 113 | L57: 15 | M57: 5.4380793 | N57: 5.3936275 | O57: 5.4234952 | P57: 8.2380082 | Q57: 0 | R57: 1 | S57: 5986 | T57: 4.7298626 | U57: 2.4466854
A58: 45593 | B58: 240 | C58: 220 | D58: 226.67 | E58: Diwali (peak week) | F58: 103.98 | G58: 145.57 | H58: Regular increase | I58: 5250 | J58: =K58/2 -> 55.5 | K58: 111 | L58: 15 | M58: 5.4806389 | N58: 5.3936275 | O58: 5.4234952 | P58: 8.5659834 | Q58: 1 | R58: 0 | S58: 4922 | T58: 4.7083583 | U58: 2.5344901
A59: 45600 | B59: 240 | C59: 220 | D59: 226.67 | F59: 104.04 | G59: 145.66 | I59: 2730 | J59: =K59/2 -> 55 | K59: 110 | L59: 15 | M59: 5.4806389 | N59: 5.3936275 | O59: 5.4234952 | P59: 7.9120569 | Q59: 0 | R59: 0 | S59: 2374 | T59: 4.7037477 | U59: 2.3427669
A60: 45607 | B60: 240 | C60: 220 | D60: 236.67 | F60: 104.1 | G60: 145.74 | I60: 2482 | J60: =K60/2 -> 54.5 | K60: 109 | L60: 16 | M60: 5.4806389 | N60: 5.3936275 | O60: 5.4666668 | P60: 7.81682 | Q60: 0 | R60: 0 | S60: 2339 | T60: 4.6948281 | U60: 2.2793165
A61: 45614 | B61: 240 | C61: 220 | D61: 236.67 | F61: 104.16 | G61: 145.82 | I61: 2311 | J61: =K61/2 -> 54.5 | K61: 109 | L61: 14 | M61: 5.4806389 | N61: 5.3936275 | O61: 5.4666668 | P61: 7.7454356 | Q61: 0 | R61: 0 | S61: 2726 | T61: 4.6898789 | U61: 2.2267834
A62: 45621 | B62: 240 | C62: 220 | D62: 236.67 | F62: 104.22 | G62: 145.9 | I62: 2587 | J62: =K62/2 -> 56 | K62: 112 | L62: 13 | M62: 5.4806389 | N62: 5.3936275 | O62: 5.4666668 | P62: 7.8582542 | Q62: 0 | R62: 0 | S62: 2300 | T62: 4.7144729 | U62: 2.3997118
A63: 45628 | B63: 240 | C63: 220 | D63: 236.67 | F63: 104.28 | G63: 145.99 | I63: 2504 | J63: =K63/2 -> 55 | K63: 110 | L63: 12 | M63: 5.4806389 | N63: 5.3936275 | O63: 5.4666668 | P63: 7.8256447 | Q63: 0 | R63: 0 | S63: 2427 | T63: 4.6972935 | U63: 2.3551775
A64: 45635 | B64: 240 | C64: 220 | D64: 236.67 | F64: 104.34 | G64: 146.07 | I64: 2428 | J64: =K64/2 -> 54.5 | K64: 109 | L64: 16 | M64: 5.4806389 | N64: 5.3936275 | O64: 5.4666668 | P64: 7.7948232 | Q64: 0 | R64: 0 | S64: 2567 | T64: 4.6949195 | U64: 2.3933395
A65: 45642 | B65: 240 | C65: 220 | D65: 236.67 | F65: 104.4 | G65: 146.15 | I65: 2464 | J65: =K65/2 -> 55 | K65: 110 | L65: 16 | M65: 5.4806389 | N65: 5.3936275 | O65: 5.4666668 | P65: 7.8095413 | Q65: 0 | R65: 0 | S65: 2701 | T65: 4.7032946 | U65: 2.2823824
A66: 45649 | B66: 240 | C66: 220 | D66: 236.67 | F66: 104.45 | G66: 146.24 | I66: 2364 | J66: =K66/2 -> 54.5 | K66: 109 | L66: 15 | M66: 5.4806389 | N66: 5.3936275 | O66: 5.4666668 | P66: 7.7681104 | Q66: 0 | R66: 0 | S66: 2774 | T66: 4.6950109 | U66: 2.3095607
A67: 45656 | B67: 240 | C67: 220 | D67: 236.67 | F67: 104.51 | G67: 146.32 | I67: 2552 | J67: =K67/2 -> 55 | K67: 110 | L67: 14 | M67: 5.4806389 | N67: 5.3936275 | O67: 5.4666668 | P67: 7.8446326 | Q67: 0 | R67: 0 | S67: 2820 | T67: 4.6982962 | U67: 2.2834023
A68: 45663 | B68: 240 | C68: 220 | D68: 236.67 | F68: 104.57 | G68: 146.4 | I68: 2670 | J68: =K68/2 -> 55 | K68: 110 | L68: 14 | M68: 5.4806389 | N68: 5.3936275 | O68: 5.4666668 | P68: 7.8898338 | Q68: 0 | R68: 0 | S68: 2602 | T68: 4.701389 | U68: 2.2935443
A69: 45670 | B69: 240 | C69: 220 | D69: 236.67 | F69: 104.63 | G69: 146.49 | I69: 2823 | J69: =K69/2 -> 55.5 | K69: 111 | L69: 10 | M69: 5.4806389 | N69: 5.3936275 | O69: 5.4666668 | P69: 7.9455554 | Q69: 0 | R69: 0 | S69: 2523 | T69: 4.7077268 | U69: 2.3813963
A70: 45677 | B70: 240 | C70: 220 | D70: 236.67 | F70: 104.69 | G70: 146.57 | I70: 2588 | J70: =K70/2 -> 55 | K70: 110 | L70: 10.01 | M70: 5.4806389 | N70: 5.3936275 | O70: 5.4666668 | P70: 7.8586407 | Q70: 0 | R70: 0 | S70: 2770 | T70: 4.7038384 | U70: 2.3035846
... A75: 45712 | B75: 240 | C75: 220 | D75: 236.67 | F75: 104.99 | G75: 146.99 | I75: 2717 | J75: =K75/2 -> 58.5 | K75: 117 | L75: 15 | M75: 5.4806389 | N75: 5.3936275 | O75: 5.4666668 | P75: 7.9072836 | Q75: 0 | R75: 0 | S75: 2677 | T75: 4.7639672 | U75: 2.442347
A76: 45719 | B76: 240 | C76: 220 | D76: 236.67 | E76: Holi (build-up) | F76: 105.05 | G76: 147.07 | I76: 3471 | J76: =K76/2 -> 58.5 | K76: 117 | L76: 16 | M76: 5.4806389 | N76: 5.3936275 | O76: 5.4666668 | P76: 8.152198 | Q76: 0 | R76: 1 | S76: 2876 | T76: 4.763199 | U76: 2.5257286
A77: 45726 | B77: 240 | C77: 220 | D77: 236.67 | E77: Holi (peak week) | F77: 105.11 | G77: 147.15 | I77: 5240 | J77: =K77/2 -> 58 | K77: 116 | L77: 15 | M77: 5.4806389 | N77: 5.3936275 | O77: 5.4666668 | P77: 8.5640768 | Q77: 1 | R77: 0 | S77: 3537 | T77: 4.7537626 | U77: 2.6720775
A78: 45733 | B78: 240 | C78: 230 | D78: 236.67 | F78: 105.17 | G78: 147.24 | I78: 2680 | J78: =K78/2 -> 57.5 | K78: 115 | L78: 14 | M78: 5.4806389 | N78: 5.4380793 | O78: 5.4666668 | P78: 7.8935721 | Q78: 0 | R78: 0 | S78: 2385 | T78: 4.7454537 | U78: 2.2575877
A79: 45740 | B79: 240 | C79: 230 | D79: 236.67 | F79: 105.23 | G79: 147.32 | I79: 2807 | J79: =K79/2 -> 57.5 | K79: 115 | L79: 16 | M79: 5.4806389 | N79: 5.4380793 | O79: 5.4666668 | P79: 7.9398716 | Q79: 0 | R79: 0 | S79: 2576 | T79: 4.7489241 | U79: 2.3379522
A80: 45747 | B80: 240 | C80: 230 | D80: 236.67 | F80: 105.29 | G80: 147.4 | I80: 2982 | J80: =K80/2 -> 57.5 | K80: 115 | L80: 17 | M80: 5.4806389 | N80: 5.4380793 | O80: 5.4666668 | P80: 8.0003495 | Q80: 0 | R80: 0 | S80: 2695 | T80: 4.7414478 | U80: 2.4353662
A81: 45754 | B81: 240 | C81: 230 | D81: 236.67 | F81: 105.35 | G81: 147.49 | I81: 2672 | J81: =K81/2 -> 57.5 | K81: 115 | L81: 16 | M81: 5.4806389 | N81: 5.4380793 | O81: 5.4666668 | P81: 7.8905825 | Q81: 0 | R81: 0 | S81: 2549 | T81: 4.7462356 | U81: 2.3702437
A82: 45761 | B82: 240 | C82: 230 | D82: 236.67 | F82: 105.41 | G82: 147.57 | I82: 2574 | J82: =K82/2 -> 56.5 | K82: 113 | L82: 17 | M82: 5.4806389 | N82: 5.4380793 | O82: 5.4666668 | P82: 7.8532164 | Q82: 0 | R82: 0 | S82: 2663 | T82: 4.7234864 | U82: 2.3841651
A83: 45768 | B83: 240 | C83: 230 | D83: 236.67 | F83: 105.47 | G83: 147.66 | I83: 2738 | J83: =K83/2 -> 57.5 | K83: 115 | L83: 18 | M83: 5.4806389 | N83: 5.4380793 | O83: 5.4666668 | P83: 7.914983 | Q83: 0 | R83: 0 | S83: 2482 | T83: 4.745193 | U83: 2.3551775
A84: 45775 | B84: 240 | C84: 230 | D84: 236.67 | F84: 105.53 | G84: 147.74 | I84: 2977 | J84: =K84/2 -> 58.5 | K84: 117 | L84: 16 | M84: 5.4806389 | N84: 5.4380793 | O84: 5.4666668 | P84: 7.9986714 | Q84: 0 | R84: 0 | S84: 2491 | T84: 4.7590065 | U84: 2.4714836
A85: 45782 | B85: 250 | C85: 230 | D85: 236.67 | F85: 105.59 | G85: 147.82 | H85: Regular increase | I85: 2661 | J85: =K85/2 -> 58 | K85: 116 | L85: 17 | M85: 5.5214609 | N85: 5.4380793 | O85: 5.4666668 | P85: 7.8864573 | Q85: 0 | R85: 0 | S85: 2177 | T85: 4.7561731 | U85: 2.3786198
A86: 45789 | B86: 250 | C86: 230 | D86: 236.67 | F86: 105.65 | G86: 147.91 | I86: 2706 | J86: =K86/2 -> 59 | K86: 118 | L86: 18 | M86: 5.5214609 | N86: 5.4380793 | O86: 5.4666668 | P86: 7.9032268 | Q86: 0 | R86: 0 | S86: 2051 | T86: 4.7678841 | U86: 2.2049723
A87: 45796 | B87: 250 | C87: 230 | D87: 236.67 | F87: 105.71 | G87: 147.99 | I87: 2779 | J87: =K87/2 -> 59 | K87: 118 | L87: 16 | M87: 5.5214609 | N87: 5.4380793 | O87: 5.4666668 | P87: 7.9298464 | Q87: 0 | R87: 0 | S87: 2295 | T87: 4.7678841 | U87: 2.3272777
A88: 45803 | B88: 250 | C88: 230 | D88: 236.67 | F88: 105.77 | G88: 148.08 | I88: 2634 | J88: =K88/2 -> 60.5 | K88: 121 | L88: 17 | M88: 5.5214609 | N88: 5.4380793 | O88: 5.4666668 | P88: 7.8762589 | Q88: 0 | R88: 0 | S88: 2210 | T88: 4.7967818 | U88: 2.225704
A89: 45810 | B89: 250 | C89: 230 | D89: 236.67 | F89: 105.83 | G89: 148.16 | I89: 2509 | J89: =K89/2 -> 60.5 | K89: 121 | L89: 18 | M89: 5.5214609 | N89: 5.4380793 | O89: 5.4666668 | P89: 7.8276395 | Q89: 0 | R89: 0 | S89: 2272 | T89: 4.7986789 | U89: 2.1246539
A90: 45817 | B90: 250 | C90: 230 | D90: 236.67 | F90: 105.89 | G90: 148.25 | I90: 2922 | J90: =K90/2 -> 61.5 | K90: 123 | L90: 18 | M90: 5.5214609 | N90: 5.4380793 | O90: 5.4666668 | P90: 7.9800236 | Q90: 0 | R90: 0 | S90: 2379 | T90: 4.8134031 | U90: 2.3427669
A91: 45824 | B91: 250 | C91: 230 | D91: 236.67 | F91: 105.95 | G91: 148.33 | I91: 2978 | J91: =K91/2 -> 60 | K91: 120 | L91: 19 | M91: 5.5214609 | N91: 5.4380793 | O91: 5.4666668 | P91: 7.9990072 | Q91: 0 | R91: 0 | S91: 2300 | T91: 4.7844872 | U91: 2.4923787
A92: 45831 | B92: 250 | C92: 230 | D92: 236.67 | F92: 106.01 | G92: 148.41 | I92: 2623 | J92: =K92/2 -> 59.5 | K92: 119 | L92: 18 | M92: 5.5214609 | N92: 5.4380793 | O92: 5.4666668 | P92: 7.872074 | Q92: 0 | R92: 0 | S92: 2200 | T92: 4.7824792 | U92: 2.390596
A93: 45838 | B93: 250 | C93: 230 | D93: 236.67 | F93: 106.07 | G93: 148.5 | I93: 2720 | J93: =K93/2 -> 58.5 | K93: 117 | L93: 17 | M93: 5.5214609 | N93: 5.4380793 | O93: 5.4666668 | P93: 7.9083872 | Q93: 0 | R93: 0 | S93: 2100 | T93: 4.7635405 | U93: 2.2945529
A94: 45845 | B94: 250 | C94: 230 | D94: 236.67 | F94: 106.13 | G94: 148.58 | I94: 2646 | J94: =K94/2 -> 56.5 | K94: 113 | L94: 19 | M94: 5.5214609 | N94: 5.4380793 | O94: 5.4666668 | P94: 7.8808043 | Q94: 0 | R94: 0 | S94: 2200 | T94: 4.7315385 | U94: 2.313525
A95: 45852 | B95: 250 | C95: 230 | D95: 236.67 | F95: 106.19 | G95: 148.67 | I95: 2903 | J95: =K95/2 -> 57 | K95: 114 | L95: 19 | M95: 5.5214609 | N95: 5.4380793 | O95: 5.4666668 | P95: 7.9735 | Q95: 0 | R95: 0 | S95: 2145 | T95: 4.7338272 | U95: 2.4798941
A96: 45859 | B96: 250 | C96: 230 | D96: 236.67 | F96: 106.25 | G96: 148.75 | I96: 2596 | J96: =K96/2 -> 55.5 | K96: 111 | L96: 20 | M96: 5.5214609 | N96: 5.4380793 | O96: 5.4666668 | P96: 7.8617271 | Q96: 0 | R96: 0 | S96: 2222 | T96: 4.7112405 | U96: 2.403335
A97: 45866 | B97: 250 | C97: 230 | D97: 236.67 | E97: Raksha Bandhan (build-up) | F97: 138.21 | G97: 160 | I97: 3429 | J97: =K97/2 -> 56 | K97: 112 | L97: 18 | M97: 5.5214609 | N97: 5.4380793 | O97: 5.4666668 | P97: 8.140024 | Q97: 0 | R97: 1 | S97: 2100 | T97: 4.7152794 | U97: 2.5564518
A98: 45873 | B98: 250 | C98: 230 | D98: 236.67 | E98: Raksha Bandhan (peak week) | F98: 138.28 | G98: 160.09 | I98: 4749 | J98: =K98/2 -> 57 | K98: 114 | L98: 19 | M98: 5.5214609 | N98: 5.4380793 | O98: 5.4666668 | P98: 8.4656893 | Q98: 1 | R98: 0 | S98: 2300 | T98: 4.7378637 | U98: 2.6885275
A99: 45880 | B99: 260 | C99: 230 | D99: 236.67 | F99: 138.36 | G99: 160.18 | H99: Oil-shock increase | I99: 2739 | J99: =K99/2 -> 57.5 | K99: 115 | L99: 12 | M99: 5.5606816 | N99: 5.4380793 | O99: 5.4666668 | P99: 7.9153482 | Q99: 0 | R99: 0 | S99: 2160 | T99: 4.7453668 | U99: 2.3969858
A100: 45887 | B100: 260 | C100: 240 | D100: 246.67 | F100: 138.44 | G100: 160.27 | I100: 2658 | J100: =K100/2 -> 57 | K100: 114 | L100: 14 | M100: 5.5606816 | N100: 5.4806389 | O100: 5.5080514 | P100: 7.8853292 | Q100: 0 | R100: 0 | S100: 2412 | T100: 4.7351453 | U100: 2.4587338
A101: 45894 | B101: 260 | C101: 240 | D101: 246.67 | F101: 138.52 | G101: 160.36 | I101: 2891 | J101: =K101/2 -> 58.5 | K101: 117 | L101: 16 | M101: 5.5606816 | N101: 5.4806389 | O101: 5.5080514 | P101: 7.9693577 | Q101: 0 | R101: 0 | S101: 2260 | T101: 4.7606343 | U101: 2.4397349
A102: 45901 | B102: 260 | C102: 240 | D102: 256.67 | F102: 138.6 | G102: 160.45 | I102: 2808 | J102: =K102/2 -> 60.5 | K102: 121 | L102: 17 | M102: 5.5606816 | N102: 5.4806389 | O102: 5.5477912 | P102: 7.9402278 | Q102: 0 | R102: 0 | S102: 2435 | T102: 4.7940535 | U102: 2.4132316
A103: 45908 | B103: 260 | C103: 240 | D103: 256.67 | F103: 138.68 | G103: 160.55 | I103: 2738 | J103: =K103/2 -> 60.5 | K103: 121 | L103: 18 | M103: 5.5606816 | N103: 5.4806389 | O103: 5.5477912 | P103: 7.914983 | Q103: 0 | R103: 0 | S103: 2792 | T103: 4.7974421 | U103: 2.313525
A104: 45915 | B104: 260 | C104: 240 | D104: 256.67 | F104: 138.76 | G104: 160.64 | I104: 2667 | J104: =K104/2 -> 61 | K104: 122 | L104: 17 | M104: 5.5606816 | N104: 5.4806389 | O104: 5.5477912 | P104: 7.8887095 | Q104: 0 | R104: 0 | S104: 2569 | T104: 4.8080294 | U104: 2.4388627
A105: 45922 | B105: 260 | C105: 240 | D105: 256.67 | E105: Diwali (build-up) | F105: 138.83 | G105: 160.73 | I105: 3596 | J105: =K105/2 -> 62 | K105: 124 | L105: 16 | M105: 5.5606816 | N105: 5.4806389 | O105: 5.5477912 | P105: 8.1875774 | Q105: 0 | R105: 1 | S105: 3548 | T105: 4.816565 | U105: 2.5055259
A106: 45929 | B106: 260 | C106: 240 | D106: 256.67 | E106: Diwali (build-up) | F106: 133.57 | G106: 158.95 | I106: 3898 | J106: =K106/2 -> 60.5 | K106: 121 | L106: 16 | M106: 5.5606816 | N106: 5.4806389 | O106: 5.5477912 | P106: 8.2682189 | Q106: 0 | R106: 1 | S106: 3922 | T106: 4.7968643 | U106: 2.6490077
A107: 45936 | B107: 260 | C107: 240 | D107: 256.67 | E107: Diwali (build-up) | F107: 128.3 | G107: 157.17 | I107: 3454 | J107: =K107/2 -> 60.5 | K107: 121 | L107: 16 | M107: 5.5606816 | N107: 5.4806389 | O107: 5.5477912 | P107: 8.1472883 | Q107: 0 | R107: 1 | S107: 5028 | T107: 4.7961211 | U107: 2.4604432
A108: 45943 | B108: 260 | C108: 240 | D108: 256.67 | E108: Diwali (build-up) | F108: 123.03 | G108: 155.39 | I108: 3854 | J108: =K108/2 -> 61 | K108: 122 | L108: 17 | M108: 5.5606816 | N108: 5.4806389 | O108: 5.5477912 | P108: 8.2568668 | Q108: 0 | R108: 1 | S108: 6234 | T108: 4.8047585 | U108: 2.5525653
A109: 45950 | B109: 260 | C109: 240 | D109: 256.67 | E109: Diwali (peak week) | F109: 117.74 | G109: 153.6 | I109: 5455 | J109: =K109/2 -> 61 | K109: 122 | L109: 18 | M109: 5.5606816 | N109: 5.4806389 | O109: 5.5477912 | P109: 8.6042879 | Q109: 1 | R109: 0 | S109: 5459 | T109: 4.8045127 | U109: 2.7027026
A110: 45957 | B110: 260 | C110: 240 | D110: 256.67 | F110: 112.46 | G110: 151.81 | I110: 2561 | J110: =K110/2 -> 60 | K110: 120 | L110: 16 | M110: 5.5606816 | N110: 5.4806389 | O110: 5.5477912 | P110: 7.8481531 | Q110: 0 | R110: 0 | S110: 2336 | T110: 4.7869916 | U110: 2.2975726
A111: 45964 | B111: 260 | C111: 240 | D111: 256.67 | F111: 107.16 | G111: 150.03 | I111: 2770 | J111: =K111/2 -> 60.5 | K111: 121 | L111: 17 | M111: 5.5606816 | N111: 5.4806389 | O111: 5.5477912 | P111: 7.9266026 | Q111: 0 | R111: 0 | S111: 2395 | T111: 4.7942191 | U111: 2.5423891
A112: 45971 | B112: 260 | C112: 240 | D112: 256.67 | F112: 107.22 | G112: 150.11 | I112: 2725 | J112: =K112/2 -> 60 | K112: 120 | L112: 18 | M112: 5.5606816 | N112: 5.4806389 | O112: 5.5477912 | P112: 7.9102237 | Q112: 0 | R112: 0 | S112: 2837 | T112: 4.7879083 | U112: 2.5225235
A113: 45978 | B113: 260 | C113: 240 | D113: 256.67 | F113: 107.28 | G113: 150.2 | I113: 2668 | J113: =K113/2 -> 60.5 | K113: 121 | L113: 19 | M113: 5.5606816 | N113: 5.4806389 | O113: 5.5477912 | P113: 7.8890844 | Q113: 0 | R113: 0 | S113: 2901 | T113: 4.7931424 | U113: 2.3693087
...

Sheet montecarlo
A1: shelf | B1: legal | C1: pretax_ok | D1: E_units | E1: E_profit | F1: P5 | G1: P95 | H1: CVaR5 | I1: P_minvol | J1: P_minprofit | K1: P_joint | L1: P_over_cap | M1: P_over_maxprofit
A2: 288 | B2: needs new MRP | C2: TRUE | D2: 13032.507 | E2: 762492.76 | F2: 613761.1 | G2: 919529.02 | H2: 580589.47 | I2: 0.50944 | J2: 0.88738 | K2: 0.50016 | L2: 0 | M2: 0.17204
A3: 287 | B3: needs new MRP | C3: TRUE | D3: 13087.675 | E3: 756399.19 | F3: 607486.33 | G3: 913520.74 | H3: 574549.52 | I3: 0.5406 | J3: 0.87412 | K3: 0.52636 | L3: 0 | M3: 0.1567
A4: 286 | B4: needs new MRP | C4: TRUE | D4: 13143.281 | E4: 750250.86 | F4: 601295.8 | G4: 907569.1 | H4: 568440.05 | I4: 0.57404 | J4: 0.8586 | K4: 0.55256 | L4: 0 | M4: 0.14252
A5: 285 | B5: needs new MRP | C5: TRUE | D5: 13199.328 | E5: 744047.1 | F5: 595043.38 | G5: 901290.98 | H5: 562258.52 | I5: 0.60658 | J5: 0.8432 | K5: 0.57656 | L5: 0 | M5: 0.1295
A6: 284 | B6: needs new MRP | C6: TRUE | D6: 13255.822 | E6: 737787.25 | F6: 588684.66 | G6: 894962.6 | H6: 556002.99 | I6: 0.63806 | J6: 0.8266 | K6: 0.59666 | L6: 0 | M6: 0.11644
A7: 283 | B7: needs new MRP | C7: TRUE | D7: 13312.768 | E7: 731470.6 | F7: 582505.74 | G7: 888636.56 | H7: 549672.91 | I7: 0.67002 | J7: 0.8074 | K7: 0.61398 | L7: 0 | M7: 0.10436
A8: 282 | B8: needs new MRP | C8: TRUE | D8: 13370.171 | E8: 725096.46 | F8: 576184.41 | G8: 882163.76 | H8: 543265.89 | I8: 0.69958 | J8: 0.78686 | K8: 0.62588 | L8: 0 | M8: 0.09294
A9: 281 | B9: needs new MRP | C9: TRUE | D9: 13428.037 | E9: 718664.13 | F9: 569693.05 | G9: 875791.99 | H9: 536781.48 | I9: 0.72822 | J9: 0.76618 | K9: 0.63466 | L9: 0 | M9: 0.08228
A10: 280 | B10: ok | C10: TRUE | D10: 13486.372 | E10: 712172.86 | F10: 563062.72 | G10: 869430.89 | H10: 530220.24 | I10: 0.75522 | J10: 0.74264 | K10: 0.6362 | L10: 0 | M10: 0.07276
A11: 279 | B11: ok | C11: TRUE | D11: 13545.18 | E11: 705621.94 | F11: 556412.66 | G11: 863227.94 | H11: 523584.51 | I11: 0.78182 | J11: 0.71924 | K11: 0.63516 | L11: 0 | M11: 0.06432
A12: 278 | B12: ok | C12: TRUE | D12: 13604.467 | E12: 699010.62 | F12: 549571.06 | G12: 856664.32 | H12: 516871.84 | I12: 0.80538 | J12: 0.69304 | K12: 0.627 | L12: 0 | M12: 0.05682
A13: 277 | B13: ok | C13: TRUE | D13: 13664.239 | E13: 692338.11 | F13: 542830.69 | G13: 849921.97 | H13: 510086.02 | I13: 0.82762 | J13: 0.66624 | K13: 0.6153 | L13: 2e-05 | M13: 0.05
... A25: 265 | B25: ok | C25: TRUE | D25: 14421.323 | E25: 607189.89 | F25: 455903.61 | G25: 766992.64 | H25: 422529.25 | I25: 0.97522 | J25: 0.31906 | K25: 0.3189 | L25: 0.0008 | M25: 0.0067

Sheet Definitions
A1: 05 — DEFINITIONS FOR NON-ECONICS USERS
A3: Term | B3: Simple definition | C3: Examples | D3: Use in pricing model | E3: Usually entered as | F3: Notes
A4: Fixed cost | B4: Generally stable with unit volume within the selected operating range and period. | C4: Rent, permanent salaries, insurance, depreciation | D4: Period-level cost; used in break-even and profit optimization | E4: ₹ / period | F4: Can become step/mixed at capacity thresholds.
A5: Variable cost | B5: Generally changes with units produced or sold. | C5: Raw material, packaging, per-unit logistics, marketplace fee | D5: Cost per unit / function of quantity | E5: ₹ / unit | F5: Packaging is usually variable when one package is needed per unit.
A6: Packaging cost | B6: Physical packaging and consumables. | C6: Pouch, carton, label, seal, bottle, cap, tray | D6: Variable cost per unit | E6: ₹ / unit | F6: Separate it for transparency and optimization.
A7: Fixed labour | B7: Labour cost not directly scaling with units in the relevant range. | C7: Plant manager salary, permanent admin salary | D7: Fixed cost / period | E7: ₹ / period | F7: May become semi-variable with overtime or extra shifts.
A8: Variable labour | B8: Labour paid in proportion to output or directly productive hours. | C8: Piece-rate workers, output-linked packing labour | D8: Variable cost / unit or function of Q | E8: ₹ / unit | F8: Useful for operations-aware pricing.
A9: Step / semi-variable cost | B9: Cost changes in jumps after a threshold. | C9: Overtime, second shift, extra warehouse | D9: Piecewise cost function | E9: Rule / amount | F9: Keep separate where a simple fixed/variable classification is misleading.
A10: Target volume / period | B10: Expected saleable units during the selected planning/cost period. | C10: 10,000 units/month | D10: Fixed-cost allocation and break-even analysis | E10: units / period | F10: Planning assumption; not the final demand forecast.
A11: Minimum production | B11: Lowest feasible or contracted volume in a period. | C11: 1,000 units/month | D11: Hard optimization constraint | E11: units / period | F11: Use only if operationally/contractually real.
A12: Maximum production | B12: Physical/operational output ceiling in a period. | C12: 10,000 units/month | D12: Hard optimization constraint | E12: units / period | F12: Can come from equipment, labour or storage.
A13: GST / tax | B13: Tax rate applied to the relevant tax base. | C13: 5%, 12%, 18% | D13: Separates base price from customer-facing price | E13: % | F13: Actual applicability must be validated for the product/jurisdiction.
A14: Price leader | B14: Competitor whose pricing provides an important market reference. | C14: Largest brand in a category | D14: Relative price / competitive response features | E14: Name + price | F14: Leadership is a market fact, not automatically a pricing target.
A15: Price elasticity | B15: Approximate % change in demand from a 1% price change. | C15: Elasticity = -1.5 | D15: Demand response estimation | E15: Estimated later | F15: Use company evidence first; external values are priors/sanity checks.

Sheet Dashboard
A1: PRICING CONTEXT — LIVE SUMMARY
A3: Metric | B3: Value | C3: Metric | D3: Value | E3: Metric | F3: Value | G3: Metric | H3: Value
A4: Company | B4: =Company_Context!B5 -> bishanlal babulal | C4: Product | D4: =Company_Context!B7 -> 1kg bikaneri bhujia | E4: Period | F4: =Company_Context!B11 -> rajasthan particulary bikaner | G4: Readiness | H4: =#REF! -> #REF!
A5: Current base price | B5: =Company_Context!B16 -> 267 | C5: GST % | D5: =Company_Context!B17 -> 5 | E5: Customer price | F5: =Company_Context!B22 -> 280.35 | G5: Leader | H5: =Company_Context!F6 -> bikaji
A6: Variable cost / unit | B6: =Cost_Structure!C18 -> 180.7 | C6: Fixed cost / period | D6: =Cost_Structure!C30 -> 448000 | E6: Target volume | F6: =Cost_Structure!B6 -> 15000 | G6: Break-even volume | H6: =Cost_Structure!B41 -> 56.433333
A7: Full cost / unit | B7: =Cost_Structure!B39 -> 210.56667 | C7: Contribution / unit | D7: =Cost_Structure!B40 -> 86.3 | E7: Effective max capacity | F7: =#REF! -> #REF! | G7: Min margin | H7: =#REF! -> #REF!
A8: Min production | B8: =#REF! -> #REF! | C8: Max production | D8: =#REF! -> #REF! | E8: Supplier MOQ | F8: =#REF! -> #REF! | G8: Max price vs leader | H8: =#REF! -> #REF!
A11: How the workbook feeds the pricing engine
A12: Stage | B12: Uses this workbook | C12: Output | D12: Next step
A13: 1. Context | B13: Company + product + leader + tax | C13: Structured pricing profile | D13: Validate data
A14: 2. Cost | B14: Variable + fixed + packaging + labour | C14: Cost function + break-even | D14: Constrain optimization
A15: 3. Demand | B15: Historical price + quantity + context | C15: Forecast + demand response | D15: Elasticity / causal models
A16: 4. Competition | B16: Leader / competitor prices | C16: Relative price + leader gap | D16: Competitive constraints
A17: 5. Optimization | B17: Demand + cost + constraints | C17: Candidate price set | D17: Sensitivity + Monte Carlo
A18: 6. Explanation | B18: Model outputs + context | C18: Human-readable explanation | D18: Human review / decision
